[
  {
    "_id": "1760511004173cawo826ai",
    "buyOrder": "tk003876nt-123er-456",
    "sessionId": "s003876oy4j4z",
    "amount": 19990,
    "currency": "CLP",
    "userId": "test-user-456",
    "contentId": "test-content-123",
    "token": "01ab4cec0cfc06b8e754a946aeb636d455925793373e964d17e9d44c672475a9",
    "url": "https://webpay3gint.transbank.cl/webpayserver/initTransaction",
    "status": "completed",
    "createdAt": "2025-10-15T06:50:04.173Z",
    "updatedAt": "2025-10-15T06:50:33.564Z"
  },
  {
    "_id": "1760511250390sgrnb2sde",
    "buyOrder": "tk250193nt-123er-456",
    "sessionId": "s250194vsjhbu",
    "amount": 19990,
    "currency": "CLP",
    "userId": "test-user-456",
    "contentId": "test-content-123",
    "token": "01ab125e1f7462b6833770c0befefcdc4d8b79ea416797fc7d8a8b8fe912a903",
    "url": "https://webpay3gint.transbank.cl/webpayserver/initTransaction",
    "status": "completed",
    "createdAt": "2025-10-15T06:54:10.390Z",
    "updatedAt": "2025-10-15T06:54:30.144Z"
  },
  {
    "_id": "1760575816930bbi28vln3",
    "buyOrder": "buy_1760509624867pjzjuclsj_1760575468321uo9zmwzvl_1760575816929_2ojui3f6u",
    "sessionId": "session_1760575816929_a7caotnxe",
    "amount": 2500,
    "currency": "CLP",
    "userId": "1760575468321uo9zmwzvl",
    "contentId": "1760509624867pjzjuclsj",
    "token": "1760575816929_6o195nmz3e",
    "url": "https://webpay3gint.transbank.cl/rswebpaytransaction/api/webpay/v1.2/transactions/1760575816929_6o195nmz3e",
    "status": "pending",
    "createdAt": "2025-10-16T00:50:16.930Z",
    "updatedAt": "2025-10-16T00:50:16.930Z"
  },
  {
    "_id": "1760592640805di5vfzoc2",
    "buyOrder": "tk638719nt-123er-456",
    "sessionId": "s638719vjjmlr",
    "amount": 19990,
    "currency": "CLP",
    "userId": "test-user-456",
    "contentId": "test-content-123",
    "token": "01abb8cccc5587cc5b13eea4c91c76388fee1a13fb5d152c2064f22e5b812897",
    "url": "https://webpay3gint.transbank.cl/webpayserver/initTransaction",
    "status": "completed",
    "createdAt": "2025-10-16T05:30:40.805Z",
    "updatedAt": "2025-10-16T05:31:10.244Z"
  },
  {
    "_id": "1760592694103pzd584v4g",
    "buyOrder": "buy_1760575627002e5n9n1vby_1760508654867qjtn6oj03_1760592694103_gl7s75v3x",
    "sessionId": "session_1760592694103_rijowth0u",
    "amount": 1700,
    "currency": "CLP",
    "userId": "1760508654867qjtn6oj03",
    "contentId": "1760575627002e5n9n1vby",
    "token": "1760592694103_u5rzsc2du5s",
    "url": "https://webpay3gint.transbank.cl/rswebpaytransaction/api/webpay/v1.2/transactions/1760592694103_u5rzsc2du5s",
    "status": "pending",
    "createdAt": "2025-10-16T05:31:34.103Z",
    "updatedAt": "2025-10-16T05:31:34.103Z"
  },
  {
    "_id": "1760592920611cenvb51e6",
    "buyOrder": "buy_1760575627002e5n9n1vby_1760508654867qjtn6oj03_1760592920610_basp5ozaa",
    "sessionId": "session_1760592920610_ndmdit78m",
    "amount": 1700,
    "currency": "CLP",
    "userId": "1760508654867qjtn6oj03",
    "contentId": "1760575627002e5n9n1vby",
    "token": "1760592920610_syxjxdyydj",
    "url": "https://webpay3gint.transbank.cl/rswebpaytransaction/api/webpay/v1.2/transactions/1760592920610_syxjxdyydj",
    "status": "pending",
    "createdAt": "2025-10-16T05:35:20.611Z",
    "updatedAt": "2025-10-16T05:35:20.611Z"
  },
  {
    "_id": "1760593062431hbpd85grq",
    "buyOrder": "tk061930nt-123er-456",
    "sessionId": "s061930lvd9dd",
    "amount": 19990,
    "currency": "CLP",
    "userId": "test-user-456",
    "contentId": "test-content-123",
    "token": "01ab39b0a2c762ece846754dbb0af8548dfcd32ae24dea51c37913d876f76bfa",
    "url": "https://webpay3gint.transbank.cl/webpayserver/initTransaction",
    "status": "pending",
    "createdAt": "2025-10-16T05:37:42.431Z",
    "updatedAt": "2025-10-16T05:37:42.431Z"
  },
  {
    "_id": "1760593075941us0ouz39p",
    "buyOrder": "buy_1760575627002e5n9n1vby_1760508654867qjtn6oj03_1760593075941_ayu9t5ubn",
    "sessionId": "session_1760593075941_kz0cz8dw2",
    "amount": 1700,
    "currency": "CLP",
    "userId": "1760508654867qjtn6oj03",
    "contentId": "1760575627002e5n9n1vby",
    "token": "1760593075941_nswc1hcpgig",
    "url": "https://webpay3gint.transbank.cl/rswebpaytransaction/api/webpay/v1.2/transactions/1760593075941_nswc1hcpgig",
    "status": "pending",
    "createdAt": "2025-10-16T05:37:55.941Z",
    "updatedAt": "2025-10-16T05:37:55.941Z"
  },
  {
    "_id": "1760593146139jwslrmmgt",
    "buyOrder": "buy_1760575627002e5n9n1vby_1760508654867qjtn6oj03_1760593146139_yxkjxp46z",
    "sessionId": "session_1760593146139_j5q02d8yr",
    "amount": 1700,
    "currency": "CLP",
    "userId": "1760508654867qjtn6oj03",
    "contentId": "1760575627002e5n9n1vby",
    "token": "1760593146139_neddhhh10k",
    "url": "https://webpay3gint.transbank.cl/rswebpaytransaction/api/webpay/v1.2/transactions/1760593146139_neddhhh10k",
    "status": "pending",
    "createdAt": "2025-10-16T05:39:06.139Z",
    "updatedAt": "2025-10-16T05:39:06.139Z"
  },
  {
    "_id": "1760593175866kkuhxbq31",
    "buyOrder": "buy_1760575627002e5n9n1vby_1760508654867qjtn6oj03_1760593175866_jo8raf56x",
    "sessionId": "session_1760593175866_bws2zzbj6",
    "amount": 1700,
    "currency": "CLP",
    "userId": "1760508654867qjtn6oj03",
    "contentId": "1760575627002e5n9n1vby",
    "token": "1760593175866_98wqqwdk2au",
    "url": "https://webpay3gint.transbank.cl/rswebpaytransaction/api/webpay/v1.2/transactions/1760593175866_98wqqwdk2au",
    "status": "pending",
    "createdAt": "2025-10-16T05:39:35.866Z",
    "updatedAt": "2025-10-16T05:39:35.866Z"
  },
  {
    "_id": "1760593784800tyopxvicf",
    "buyOrder": "tk7845369n1vbyn6oj03",
    "sessionId": "s784536bupkoi",
    "amount": 1700,
    "currency": "CLP",
    "userId": "1760508654867qjtn6oj03",
    "contentId": "1760575627002e5n9n1vby",
    "token": "01abaacde3f5992f8142053a9c837703099e8b2aef7dfec275dc04e07a46c371",
    "url": "https://webpay3gint.transbank.cl/webpayserver/initTransaction",
    "status": "completed",
    "createdAt": "2025-10-16T05:49:44.800Z",
    "updatedAt": "2025-10-16T05:50:18.669Z"
  },
  {
    "_id": "17634473016502n3bkdjf9",
    "buyOrder": "tk3014859n1vbyd07qxc",
    "sessionId": "s301486yb2ok6",
    "amount": 1700,
    "currency": "CLP",
    "userId": "1763446626656f4jd07qxc",
    "contentId": "1760575627002e5n9n1vby",
    "token": "01abbbffaefbcb8a17cb443a49c92d89d2964f793be86b0a108aa4c65796f637",
    "url": "https://webpay3gint.transbank.cl/webpayserver/initTransaction",
    "status": "completed",
    "createdAt": "2025-11-18T06:28:21.650Z",
    "updatedAt": "2025-11-18T06:30:48.066Z"
  }
]